measure_noise
